dz_locations/__init__.py
dz_locations/admin.py
dz_locations/apps.py
dz_locations/communes.json
dz_locations/models.py
dz_locations/serializers.py
dz_locations/urls.py
dz_locations/views.py
dz_locations/wilayas.json
dz_locations/management/__init__.py
dz_locations/management/commands/__init__.py
dz_locations/management/commands/newload.py
dz_locations-0.1.6.dist-info/METADATA
dz_locations-0.1.6.dist-info/WHEEL
dz_locations-0.1.6.dist-info/top_level.txt
dz_locations-0.1.6.dist-info/RECORD
