Metadata-Version: 2.4
Name: dz_locations
Version: 0.1.6
Summary: Algerian Wilaya & Commune data for Django projects
Home-page: https://github.com/khamedtaha/dz_locations
Author: Mohammed Taha Khamed
Classifier: Programming Language :: Python :: 3
Classifier: Framework :: Django
Classifier: License :: OSI Approved :: MIT License
Classifier: Operating System :: OS Independent
Requires-Dist: Django>=5.2
Requires-Dist: djangorestframework>=3.12
Dynamic: author
Dynamic: classifier
Dynamic: description
Dynamic: description-content-type
Dynamic: home-page
Dynamic: requires-dist
Dynamic: summary
